{
  "customer_info": {
    "name": "Benjamin Franklin",
    "address": "1706 Market Street, Philadelphia TX 77019",
    "phone": "(713) 555-1706",
    "email": "bfranklin@customkitchens.com",
    "job_name": "Franklin Master Kitchen",
    "job_number": "103",
    "date": "01/08/2025",
    "wood_species": "Mixed (Paint Grade & Stain Grade Maple)",
    "door_style": "103",
    "hinge_type": "Blum Soft Close Frameless 1/2\"OL",
    "overlay": "1/2\"",
    "bore_prep": true,
    "door_sizes": "Finish Sizes",
    "panel_cut": "1/4\" MDF Raised Panel",
    "outside_edge": "Standard for #103",
    "inside_edge": "Standard for #103",
    "drawer_type": "5 piece"
  },
  "door_items": [
    {
      "cabinet": 1,
      "qty": 2,
      "width": "14 1/2",
      "height": "30 1/4",
      "type": "door",
      "material": "Paint Grade",
      "notes": "Cabinet #1"
    },
    {
      "cabinet": 2,
      "qty": 2,
      "width": "15 3/4",
      "height": "30 1/4",
      "type": "door",
      "material": "Paint Grade",
      "notes": "Cabinet #2"
    },
    {
      "cabinet": 3,
      "qty": 1,
      "width": "23 7/8",
      "height": "30 1/4",
      "type": "door",
      "material": "Stain Grade Maple",
      "notes": "Cabinet #3"
    },
    {
      "cabinet": 4,
      "qty": 2,
      "width": "17 1/2",
      "height": "30 1/4",
      "type": "door",
      "material": "Stain Grade Maple",
      "notes": "Cabinet #4"
    },
    {
      "cabinet": 5,
      "qty": 2,
      "width": "11 3/4",
      "height": "24 3/4",
      "type": "door",
      "material": "Paint Grade",
      "notes": "Cabinet #5"
    },
    {
      "cabinet": 6,
      "qty": 1,
      "width": "17 7/8",
      "height": "24 3/4",
      "type": "door",
      "material": "Paint Grade",
      "notes": "Cabinet #6"
    },
    {
      "cabinet": 7,
      "qty": 2,
      "width": "14 7/8",
      "height": "24 3/4",
      "type": "door",
      "material": "Stain Grade Maple",
      "notes": "Cabinet #7"
    },
    {
      "cabinet": 8,
      "qty": 2,
      "width": "17 1/2",
      "height": "24 3/4",
      "type": "door",
      "material": "Stain Grade Maple",
      "notes": "Cabinet #8"
    },
    {
      "cabinet": 9,
      "qty": 2,
      "width": "20 3/8",
      "height": "36 1/2",
      "type": "door",
      "material": "Stain Grade Maple",
      "notes": "Cabinet #9"
    },
    {
      "cabinet": 10,
      "qty": 2,
      "width": "14 1/4",
      "height": "42 1/2",
      "type": "door",
      "material": "Paint Grade",
      "notes": "Cabinet #10"
    },
    {
      "cabinet": 11,
      "qty": 1,
      "width": "35 1/2",
      "height": "18 3/4",
      "type": "door",
      "material": "Stain Grade Maple",
      "notes": "Cabinet #11 - Horizontal"
    },
    {
      "cabinet": 12,
      "qty": 2,
      "width": "15 5/8",
      "height": "19 1/4",
      "type": "door",
      "material": "Paint Grade",
      "notes": "Cabinet #12"
    }
  ]
}